gftool/__init__.py
gftool/_util.py
gftool/_version.py
gftool/beb.py
gftool/cpa.py
gftool/density.py
gftool/fourier.py
gftool/hermpade.py
gftool/linalg.py
gftool/linearprediction.py
gftool/matrix.py
gftool/pade.py
gftool/polepade.py
gftool/precision.py
gftool/siam.py
gftool/statistics.py
gftool/basis/__init__.py
gftool/basis/pole.py
gftool/lattice/__init__.py
gftool/lattice/bcc.py
gftool/lattice/bethe.py
gftool/lattice/bethez.py
gftool/lattice/box.py
gftool/lattice/fcc.py
gftool/lattice/honeycomb.py
gftool/lattice/kagome.py
gftool/lattice/lieb.py
gftool/lattice/onedim.py
gftool/lattice/rectangular.py
gftool/lattice/sc.py
gftool/lattice/square.py
gftool/lattice/triangular.py
gftool/tests/__init__.py
gftool/tests/basis_test.py
gftool/tests/beb_test.py
gftool/tests/bethez_test.py
gftool/tests/context.py
gftool/tests/cpa_test.py
gftool/tests/fourier_test.py
gftool/tests/greenfunctions_test.py
gftool/tests/hermpade_test.py
gftool/tests/linalg_test.py
gftool/tests/linearprediction_test.py
gftool/tests/matrix_test.py
gftool/tests/old_pade.py
gftool/tests/pade_test.py
gftool/tests/polepade_test.py
gftool/tests/siam_test.py
gftool/tests/util_test.py
gftool/tests/utilities_test.py
gftool-0.11.1.dist-info/licenses/LICENSE.txt
gftool-0.11.1.dist-info/METADATA
gftool-0.11.1.dist-info/WHEEL
gftool-0.11.1.dist-info/top_level.txt
gftool-0.11.1.dist-info/RECORD
