Metadata-Version: 2.4
Name: gftool
Version: 0.11.1
Summary: Collection of commonly used Green's functions and utilities
Home-page: https://github.com/DerWeh/gftools
Author: Weh
Author-email: andreas.weh@physik.uni-augsburg.de
Project-URL: ReadTheDocs, https://gftools.readthedocs.io/
Project-URL: Source Code, https://github.com/DerWeh/gftools
Keywords: Green's function,physics
Classifier: Intended Audience :: Science/Research
Classifier: License :: OSI Approved :: MIT License
Classifier: Programming Language :: Python :: 3.7
Classifier: Programming Language :: Python :: 3.8
Classifier: Programming Language :: Python :: 3.9
Classifier: Programming Language :: Python :: 3.10
Classifier: Programming Language :: Python :: 3.11
Classifier: Programming Language :: Python :: 3.12
Classifier: Topic :: Scientific/Engineering :: Physics
Requires-Python: >=3.7
License-File: LICENSE.txt
Requires-Dist: numpy
Requires-Dist: scipy
Requires-Dist: mpmath
Dynamic: author
Dynamic: author-email
Dynamic: classifier
Dynamic: description
Dynamic: home-page
Dynamic: keywords
Dynamic: license-file
Dynamic: project-url
Dynamic: requires-dist
Dynamic: requires-python
Dynamic: summary
